amass/__init__.py
amass/cli.py
amass-0.4.1.dist-info/licenses/LICENSE
amass-0.4.1.dist-info/METADATA
amass-0.4.1.dist-info/WHEEL
amass-0.4.1.dist-info/entry_points.txt
amass-0.4.1.dist-info/top_level.txt
amass-0.4.1.dist-info/RECORD
